setup.py
gauss_bi_distributions/Binomialdistribution.py
gauss_bi_distributions/Gaussiandistribution.py
gauss_bi_distributions/Generaldistribution.py
gauss_bi_distributions/__init__.py
gauss_bi_distributions.egg-info/PKG-INFO
gauss_bi_distributions.egg-info/SOURCES.txt
gauss_bi_distributions.egg-info/dependency_links.txt
gauss_bi_distributions.egg-info/not-zip-safe
gauss_bi_distributions.egg-info/top_level.txt